pytest_prometheus/__init__.py
pytest_prometheus-0.1.dist-info/DESCRIPTION.rst
pytest_prometheus-0.1.dist-info/METADATA
pytest_prometheus-0.1.dist-info/RECORD
pytest_prometheus-0.1.dist-info/WHEEL
pytest_prometheus-0.1.dist-info/entry_points.txt
pytest_prometheus-0.1.dist-info/metadata.json
pytest_prometheus-0.1.dist-info/top_level.txt
