Metadata-Version: 2.0
Name: pytest-prometheus
Version: 0.1
Summary: Report test pass / failures to a Prometheus PushGateway
Home-page: UNKNOWN
Author: Yuvi Panda
Author-email: yuvipanda@gmail.com
License: UNKNOWN
Platform: any
Classifier: Framework :: Pytest
Requires-Dist: prometheus-client
Requires-Dist: pytest
